pysidesix_frameless_window_patch-0.0.1.dist-info/METADATA
pysidesix_frameless_window_patch-0.0.1.dist-info/WHEEL
pysidesix_frameless_window_patch-0.0.1.dist-info/licenses/LICENSE
qframeless_patch/__init__.py
pysidesix_frameless_window_patch-0.0.1.dist-info/RECORD
