Metadata-Version: 2.1
Name: pysidesix-frameless-window-patch
Version: 0.0.1
Summary: Place PySideSix-Frameless-Window titlebar into QVBoxLayout.
Author-Email: TaoChenyue <3038816978@qq.com>
License: GPL-3.0
Requires-Python: <3.10,>=3.8
Requires-Dist: PySide6>=6.4.3
Requires-Dist: PySideSix-Frameless-Window>=0.0.5
